systemics/__init__.py
systemics/chatbot/__init__.py
systemics/chatbot/chat_obj.py
systemics/chatbot/chatbot.py
systemics/chatbot/chatbot_error.py
systemics/chatbot/lm.py
systemics/chatbot/utils.py
systemics/face_recognition/__init__.py
systemics/face_recognition/face_embedding.py
systemics/face_recognition/human_cropping.py
systemics/sr/__init__.py
systemics/sr/speech_detection.py
systemics/sr/stt.py
systemics/udp/__init__.py
systemics/udp/udp_connection.py
systemics/udp/udp_error.py
systemics-0.2.1.dist-info/LICENSE
systemics-0.2.1.dist-info/METADATA
systemics-0.2.1.dist-info/WHEEL
systemics-0.2.1.dist-info/top_level.txt
systemics-0.2.1.dist-info/RECORD
