Metadata-Version: 2.1
Name: systemics
Version: 0.2.1
Summary: AI system for general agents
Home-page: https://github.com/HaShaWB/systemics
Author: HaShaWB
Author-email: whitebluej@kaist.ac.kr
Classifier: Programming Language :: Python :: 3
Classifier: License :: OSI Approved :: MIT License
Classifier: Operating System :: OS Independent
Requires-Python: >=3.10
License-File: LICENSE
Requires-Dist: numpy
Provides-Extra: face_recognition
Requires-Dist: Pillow; extra == "face-recognition"
Requires-Dist: deepface; extra == "face-recognition"
Requires-Dist: tf-keras; extra == "face-recognition"
Provides-Extra: lm
Requires-Dist: openai; extra == "lm"
Requires-Dist: pydantic; extra == "lm"
Provides-Extra: sr
Requires-Dist: webrtcvad; extra == "sr"
Requires-Dist: groq; extra == "sr"
Requires-Dist: pydub; extra == "sr"
